fasterapi/__init__.py
fasterapi/__version__.py
fasterapi/cli.py
fasterapi/scaffolder/__init__.py
fasterapi/scaffolder/generate_account.py
fasterapi/scaffolder/generate_crud.py
fasterapi/scaffolder/generate_project.py
fasterapi/scaffolder/generate_route.py
fasterapi/scaffolder/generate_schema.py
fasterapi/scaffolder/generate_service.py
fasterapi/scaffolder/generate_tokens_repo.py
fasterapi/scaffolder/mount_routes.py
fasterapi/scaffolder/templates/project_template/.env.example
fasterapi/scaffolder/templates/project_template/.gitignore
fasterapi/scaffolder/templates/project_template/Dockerfile
fasterapi/scaffolder/templates/project_template/celery_worker.py
fasterapi/scaffolder/templates/project_template/docker-compose.yml
fasterapi/scaffolder/templates/project_template/main.py
fasterapi/scaffolder/templates/project_template/readme.md
fasterapi/scaffolder/templates/project_template/requirements.txt
fasterapi/scaffolder/templates/project_template/seed.py
fasterapi/scaffolder/templates/project_template/api/__init__.py
fasterapi/scaffolder/templates/project_template/api/v1/__init__.py
fasterapi/scaffolder/templates/project_template/api/v1/admin_route.py
fasterapi/scaffolder/templates/project_template/api/v1/user_route.py
fasterapi/scaffolder/templates/project_template/core/__init__.py
fasterapi/scaffolder/templates/project_template/core/admin_logger.py
fasterapi/scaffolder/templates/project_template/core/database.py
fasterapi/scaffolder/templates/project_template/core/redis_cache.py
fasterapi/scaffolder/templates/project_template/core/scheduler.py
fasterapi/scaffolder/templates/project_template/core/task.py
fasterapi/scaffolder/templates/project_template/email_templates/__init__.py
fasterapi/scaffolder/templates/project_template/email_templates/changing_password_template.py
fasterapi/scaffolder/templates/project_template/email_templates/invitation_template.py
fasterapi/scaffolder/templates/project_template/email_templates/new_sign_in.py
nats_fasterapi-0.2.87.dist-info/LICENSE
nats_fasterapi-0.2.87.dist-info/METADATA
nats_fasterapi-0.2.87.dist-info/WHEEL
nats_fasterapi-0.2.87.dist-info/entry_points.txt
nats_fasterapi-0.2.87.dist-info/top_level.txt
nats_fasterapi-0.2.87.dist-info/RECORD
